kedia/__init__.py
kedia/abc.py
kumar/__init__.py
kumar/abc.py
varun-1.0.0.dist-info/LICENSE
varun-1.0.0.dist-info/METADATA
varun-1.0.0.dist-info/WHEEL
varun-1.0.0.dist-info/entry_points.txt
varun-1.0.0.dist-info/top_level.txt
varun-1.0.0.dist-info/RECORD
