Metadata-Version: 2.1
Name: varun
Version: 1.0.0
Summary: A Python package to get my name
Home-page: https://github.com/agmukul63
Author: Punit Modi
Author-email: puitmodi11@gmail.com
License: MIT
Platform: UNKNOWN
Classifier: License :: OSI Approved :: MIT License
Classifier: Programming Language :: Python :: 3
Classifier: Programming Language :: Python :: 3.7
